bloodHelper/__init__.py
bloodHelper/bloodHelper.py
blood_helper-0.1.0.dist-info/METADATA
blood_helper-0.1.0.dist-info/WHEEL
blood_helper-0.1.0.dist-info/top_level.txt
blood_helper-0.1.0.dist-info/RECORD
